browser_use_mcp/__init__.py
browser_use_mcp/console_tool.py
browser_use_mcp/server.py
browser_use_mcp_console-0.1.5.dist-info/METADATA
browser_use_mcp_console-0.1.5.dist-info/WHEEL
browser_use_mcp_console-0.1.5.dist-info/entry_points.txt
browser_use_mcp_console-0.1.5.dist-info/licenses/LICENSE
browser_use_mcp_console-0.1.5.dist-info/RECORD
