Metadata-Version: 2.4
Name: browser-use-mcp-console
Version: 0.1.5
Summary: MCP server for browser-use with console debugging capabilities
Project-URL: Homepage, https://github.com/archie/browser-use-mcp-console
Project-URL: Issues, https://github.com/archie/browser-use-mcp-console/issues
Project-URL: Documentation, https://github.com/archie/browser-use-mcp-console#readme
Author: archie
License-Expression: MIT
License-File: LICENSE
Keywords: ai,browser-automation,browser-use,console-debugging,mcp
Classifier: Development Status :: 4 - Beta
Classifier: Intended Audience :: Developers
Classifier: License :: OSI Approved :: MIT License
Classifier: Programming Language :: Python :: 3
Classifier: Programming Language :: Python :: 3.11
Classifier: Programming Language :: Python :: 3.12
Requires-Python: >=3.11
Requires-Dist: browser-use==0.5.6
Requires-Dist: fastmcp>=0.1.0
